<annotation>
	<folder></folder>
	<filename>crystalline_acne_--100-_jpg.rf.56a01ca873ce61eeb4fbce32141c5a55.jpg</filename>
	<path>crystalline_acne_--100-_jpg.rf.56a01ca873ce61eeb4fbce32141c5a55.jpg</path>
	<source>
		<database>roboflow.com</database>
	</source>
	<size>
		<width>1280</width>
		<height>1020</height>
		<depth>3</depth>
	</size>
	<segmented>0</segmented>
	<object>
		<name>purulent</name>
		<pose>Unspecified</pose>
		<truncated>0</truncated>
		<difficult>0</difficult>
		<occluded>0</occluded>
		<bndbox>
			<xmin>172</xmin>
			<xmax>229</xmax>
			<ymin>190</ymin>
			<ymax>265</ymax>
		</bndbox>
	</object>
	<object>
		<name>purulent</name>
		<pose>Unspecified</pose>
		<truncated>0</truncated>
		<difficult>0</difficult>
		<occluded>0</occluded>
		<bndbox>
			<xmin>252</xmin>
			<xmax>314</xmax>
			<ymin>83</ymin>
			<ymax>140</ymax>
		</bndbox>
	</object>
	<object>
		<name>purulent</name>
		<pose>Unspecified</pose>
		<truncated>0</truncated>
		<difficult>0</difficult>
		<occluded>0</occluded>
		<bndbox>
			<xmin>333</xmin>
			<xmax>402</xmax>
			<ymin>130</ymin>
			<ymax>192</ymax>
		</bndbox>
	</object>
	<object>
		<name>purulent</name>
		<pose>Unspecified</pose>
		<truncated>0</truncated>
		<difficult>0</difficult>
		<occluded>0</occluded>
		<bndbox>
			<xmin>508</xmin>
			<xmax>580</xmax>
			<ymin>105</ymin>
			<ymax>177</ymax>
		</bndbox>
	</object>
	<object>
		<name>sebo-crystan-conglo</name>
		<pose>Unspecified</pose>
		<truncated>0</truncated>
		<difficult>0</difficult>
		<occluded>0</occluded>
		<bndbox>
			<xmin>550</xmin>
			<xmax>628</xmax>
			<ymin>90</ymin>
			<ymax>275</ymax>
		</bndbox>
	</object>
	<object>
		<name>papular</name>
		<pose>Unspecified</pose>
		<truncated>0</truncated>
		<difficult>0</difficult>
		<occluded>0</occluded>
		<bndbox>
			<xmin>438</xmin>
			<xmax>505</xmax>
			<ymin>101</ymin>
			<ymax>171</ymax>
		</bndbox>
	</object>
	<object>
		<name>papular</name>
		<pose>Unspecified</pose>
		<truncated>0</truncated>
		<difficult>0</difficult>
		<occluded>0</occluded>
		<bndbox>
			<xmin>382</xmin>
			<xmax>442</xmax>
			<ymin>68</ymin>
			<ymax>132</ymax>
		</bndbox>
	</object>
	<object>
		<name>purulent</name>
		<pose>Unspecified</pose>
		<truncated>0</truncated>
		<difficult>0</difficult>
		<occluded>0</occluded>
		<bndbox>
			<xmin>128</xmin>
			<xmax>190</xmax>
			<ymin>48</ymin>
			<ymax>117</ymax>
		</bndbox>
	</object>
	<object>
		<name>cystic</name>
		<pose>Unspecified</pose>
		<truncated>0</truncated>
		<difficult>0</difficult>
		<occluded>0</occluded>
		<bndbox>
			<xmin>697</xmin>
			<xmax>1043</xmax>
			<ymin>95</ymin>
			<ymax>343</ymax>
		</bndbox>
	</object>
	<object>
		<name>folliculitis</name>
		<pose>Unspecified</pose>
		<truncated>0</truncated>
		<difficult>0</difficult>
		<occluded>0</occluded>
		<bndbox>
			<xmin>236</xmin>
			<xmax>287</xmax>
			<ymin>727</ymin>
			<ymax>789</ymax>
		</bndbox>
	</object>
	<object>
		<name>papular</name>
		<pose>Unspecified</pose>
		<truncated>0</truncated>
		<difficult>0</difficult>
		<occluded>0</occluded>
		<bndbox>
			<xmin>61</xmin>
			<xmax>106</xmax>
			<ymin>493</ymin>
			<ymax>552</ymax>
		</bndbox>
	</object>
	<object>
		<name>sebo-crystan-conglo</name>
		<pose>Unspecified</pose>
		<truncated>0</truncated>
		<difficult>0</difficult>
		<occluded>0</occluded>
		<bndbox>
			<xmin>697</xmin>
			<xmax>792</xmax>
			<ymin>694</ymin>
			<ymax>772</ymax>
		</bndbox>
	</object>
	<object>
		<name>sebo-crystan-conglo</name>
		<pose>Unspecified</pose>
		<truncated>0</truncated>
		<difficult>0</difficult>
		<occluded>0</occluded>
		<bndbox>
			<xmin>959</xmin>
			<xmax>1058</xmax>
			<ymin>792</ymin>
			<ymax>883</ymax>
		</bndbox>
	</object>
	<object>
		<name>sebo-crystan-conglo</name>
		<pose>Unspecified</pose>
		<truncated>0</truncated>
		<difficult>0</difficult>
		<occluded>0</occluded>
		<bndbox>
			<xmin>831</xmin>
			<xmax>903</xmax>
			<ymin>856</ymin>
			<ymax>936</ymax>
		</bndbox>
	</object>
	<object>
		<name>sebo-crystan-conglo</name>
		<pose>Unspecified</pose>
		<truncated>0</truncated>
		<difficult>0</difficult>
		<occluded>0</occluded>
		<bndbox>
			<xmin>878</xmin>
			<xmax>939</xmax>
			<ymin>796</ymin>
			<ymax>852</ymax>
		</bndbox>
	</object>
	<object>
		<name>sebo-crystan-conglo</name>
		<pose>Unspecified</pose>
		<truncated>0</truncated>
		<difficult>0</difficult>
		<occluded>0</occluded>
		<bndbox>
			<xmin>770</xmin>
			<xmax>852</xmax>
			<ymin>600</ymin>
			<ymax>671</ymax>
		</bndbox>
	</object>
	<object>
		<name>sebo-crystan-conglo</name>
		<pose>Unspecified</pose>
		<truncated>0</truncated>
		<difficult>0</difficult>
		<occluded>0</occluded>
		<bndbox>
			<xmin>1027</xmin>
			<xmax>1097</xmax>
			<ymin>744</ymin>
			<ymax>811</ymax>
		</bndbox>
	</object>
	<object>
		<name>sebo-crystan-conglo</name>
		<pose>Unspecified</pose>
		<truncated>0</truncated>
		<difficult>0</difficult>
		<occluded>0</occluded>
		<bndbox>
			<xmin>1050</xmin>
			<xmax>1114</xmax>
			<ymin>957</ymin>
			<ymax>1021</ymax>
		</bndbox>
	</object>
	<object>
		<name>blackhead</name>
		<pose>Unspecified</pose>
		<truncated>0</truncated>
		<difficult>0</difficult>
		<occluded>0</occluded>
		<bndbox>
			<xmin>628</xmin>
			<xmax>646</xmax>
			<ymin>765</ymin>
			<ymax>860</ymax>
		</bndbox>
	</object>
	<object>
		<name>blackhead</name>
		<pose>Unspecified</pose>
		<truncated>0</truncated>
		<difficult>0</difficult>
		<occluded>0</occluded>
		<bndbox>
			<xmin>667</xmin>
			<xmax>711</xmax>
			<ymin>933</ymin>
			<ymax>988</ymax>
		</bndbox>
	</object>
	<object>
		<name>blackhead</name>
		<pose>Unspecified</pose>
		<truncated>0</truncated>
		<difficult>0</difficult>
		<occluded>0</occluded>
		<bndbox>
			<xmin>820</xmin>
			<xmax>852</xmax>
			<ymin>704</ymin>
			<ymax>746</ymax>
		</bndbox>
	</object>
	<object>
		<name>purulent</name>
		<pose>Unspecified</pose>
		<truncated>0</truncated>
		<difficult>0</difficult>
		<occluded>0</occluded>
		<bndbox>
			<xmin>820</xmin>
			<xmax>878</xmax>
			<ymin>516</ymin>
			<ymax>563</ymax>
		</bndbox>
	</object>
	<object>
		<name>whitehead</name>
		<pose>Unspecified</pose>
		<truncated>0</truncated>
		<difficult>0</difficult>
		<occluded>0</occluded>
		<bndbox>
			<xmin>748</xmin>
			<xmax>824</xmax>
			<ymin>891</ymin>
			<ymax>966</ymax>
		</bndbox>
	</object>
	<object>
		<name>sebo-crystan-conglo</name>
		<pose>Unspecified</pose>
		<truncated>0</truncated>
		<difficult>0</difficult>
		<occluded>0</occluded>
		<bndbox>
			<xmin>715</xmin>
			<xmax>825</xmax>
			<ymin>941</ymin>
			<ymax>1017</ymax>
		</bndbox>
	</object>
	<object>
		<name>papular</name>
		<pose>Unspecified</pose>
		<truncated>0</truncated>
		<difficult>0</difficult>
		<occluded>0</occluded>
		<bndbox>
			<xmin>786</xmin>
			<xmax>843</xmax>
			<ymin>813</ymin>
			<ymax>859</ymax>
		</bndbox>
	</object>
	<object>
		<name>papular</name>
		<pose>Unspecified</pose>
		<truncated>0</truncated>
		<difficult>0</difficult>
		<occluded>0</occluded>
		<bndbox>
			<xmin>842</xmin>
			<xmax>892</xmax>
			<ymin>750</ymin>
			<ymax>798</ymax>
		</bndbox>
	</object>
</annotation>
