<annotation>
	<folder></folder>
	<filename>flat_wart_--72-_jpg.rf.baf61d530596293b15ab88aa748d26ff.jpg</filename>
	<path>flat_wart_--72-_jpg.rf.baf61d530596293b15ab88aa748d26ff.jpg</path>
	<source>
		<database>roboflow.com</database>
	</source>
	<size>
		<width>604</width>
		<height>646</height>
		<depth>3</depth>
	</size>
	<segmented>0</segmented>
	<object>
		<name>flat_wart</name>
		<pose>Unspecified</pose>
		<truncated>0</truncated>
		<difficult>0</difficult>
		<occluded>0</occluded>
		<bndbox>
			<xmin>173</xmin>
			<xmax>245</xmax>
			<ymin>81</ymin>
			<ymax>132</ymax>
		</bndbox>
	</object>
	<object>
		<name>flat_wart</name>
		<pose>Unspecified</pose>
		<truncated>0</truncated>
		<difficult>0</difficult>
		<occluded>0</occluded>
		<bndbox>
			<xmin>467</xmin>
			<xmax>535</xmax>
			<ymin>97</ymin>
			<ymax>169</ymax>
		</bndbox>
	</object>
	<object>
		<name>flat_wart</name>
		<pose>Unspecified</pose>
		<truncated>0</truncated>
		<difficult>0</difficult>
		<occluded>0</occluded>
		<bndbox>
			<xmin>500</xmin>
			<xmax>574</xmax>
			<ymin>46</ymin>
			<ymax>121</ymax>
		</bndbox>
	</object>
	<object>
		<name>flat_wart</name>
		<pose>Unspecified</pose>
		<truncated>0</truncated>
		<difficult>0</difficult>
		<occluded>0</occluded>
		<bndbox>
			<xmin>502</xmin>
			<xmax>583</xmax>
			<ymin>101</ymin>
			<ymax>181</ymax>
		</bndbox>
	</object>
	<object>
		<name>cystic</name>
		<pose>Unspecified</pose>
		<truncated>0</truncated>
		<difficult>0</difficult>
		<occluded>0</occluded>
		<bndbox>
			<xmin>162</xmin>
			<xmax>261</xmax>
			<ymin>461</ymin>
			<ymax>559</ymax>
		</bndbox>
	</object>
	<object>
		<name>cystic</name>
		<pose>Unspecified</pose>
		<truncated>0</truncated>
		<difficult>0</difficult>
		<occluded>0</occluded>
		<bndbox>
			<xmin>70</xmin>
			<xmax>132</xmax>
			<ymin>552</ymin>
			<ymax>614</ymax>
		</bndbox>
	</object>
	<object>
		<name>sebo-crystan-conglo</name>
		<pose>Unspecified</pose>
		<truncated>0</truncated>
		<difficult>0</difficult>
		<occluded>0</occluded>
		<bndbox>
			<xmin>138</xmin>
			<xmax>206</xmax>
			<ymin>218</ymin>
			<ymax>311</ymax>
		</bndbox>
	</object>
	<object>
		<name>sebo-crystan-conglo</name>
		<pose>Unspecified</pose>
		<truncated>0</truncated>
		<difficult>0</difficult>
		<occluded>0</occluded>
		<bndbox>
			<xmin>26</xmin>
			<xmax>105</xmax>
			<ymin>181</ymin>
			<ymax>268</ymax>
		</bndbox>
	</object>
	<object>
		<name>sebo-crystan-conglo</name>
		<pose>Unspecified</pose>
		<truncated>0</truncated>
		<difficult>0</difficult>
		<occluded>0</occluded>
		<bndbox>
			<xmin>90</xmin>
			<xmax>161</xmax>
			<ymin>390</ymin>
			<ymax>471</ymax>
		</bndbox>
	</object>
	<object>
		<name>blackhead</name>
		<pose>Unspecified</pose>
		<truncated>0</truncated>
		<difficult>0</difficult>
		<occluded>0</occluded>
		<bndbox>
			<xmin>66</xmin>
			<xmax>105</xmax>
			<ymin>181</ymin>
			<ymax>198</ymax>
		</bndbox>
	</object>
	<object>
		<name>papular</name>
		<pose>Unspecified</pose>
		<truncated>0</truncated>
		<difficult>0</difficult>
		<occluded>0</occluded>
		<bndbox>
			<xmin>486</xmin>
			<xmax>496</xmax>
			<ymin>328</ymin>
			<ymax>370</ymax>
		</bndbox>
	</object>
	<object>
		<name>papular</name>
		<pose>Unspecified</pose>
		<truncated>0</truncated>
		<difficult>0</difficult>
		<occluded>0</occluded>
		<bndbox>
			<xmin>525</xmin>
			<xmax>537</xmax>
			<ymin>511</ymin>
			<ymax>552</ymax>
		</bndbox>
	</object>
	<object>
		<name>papular</name>
		<pose>Unspecified</pose>
		<truncated>0</truncated>
		<difficult>0</difficult>
		<occluded>0</occluded>
		<bndbox>
			<xmin>477</xmin>
			<xmax>488</xmax>
			<ymin>546</ymin>
			<ymax>587</ymax>
		</bndbox>
	</object>
	<object>
		<name>cystic</name>
		<pose>Unspecified</pose>
		<truncated>0</truncated>
		<difficult>0</difficult>
		<occluded>0</occluded>
		<bndbox>
			<xmin>513</xmin>
			<xmax>525</xmax>
			<ymin>576</ymin>
			<ymax>618</ymax>
		</bndbox>
	</object>
	<object>
		<name>sebo-crystan-conglo</name>
		<pose>Unspecified</pose>
		<truncated>0</truncated>
		<difficult>0</difficult>
		<occluded>0</occluded>
		<bndbox>
			<xmin>508</xmin>
			<xmax>523</xmax>
			<ymin>331</ymin>
			<ymax>389</ymax>
		</bndbox>
	</object>
	<object>
		<name>sebo-crystan-conglo</name>
		<pose>Unspecified</pose>
		<truncated>0</truncated>
		<difficult>0</difficult>
		<occluded>0</occluded>
		<bndbox>
			<xmin>488</xmin>
			<xmax>507</xmax>
			<ymin>497</ymin>
			<ymax>548</ymax>
		</bndbox>
	</object>
</annotation>
