<annotation>
	<folder></folder>
	<filename>Foliculitis_--259-_jpg.rf.b0792ab5385071dcf25c66cc8ea06c41.jpg</filename>
	<path>Foliculitis_--259-_jpg.rf.b0792ab5385071dcf25c66cc8ea06c41.jpg</path>
	<source>
		<database>roboflow.com</database>
	</source>
	<size>
		<width>750</width>
		<height>605</height>
		<depth>3</depth>
	</size>
	<segmented>0</segmented>
	<object>
		<name>papular</name>
		<pose>Unspecified</pose>
		<truncated>0</truncated>
		<difficult>0</difficult>
		<occluded>0</occluded>
		<bndbox>
			<xmin>117</xmin>
			<xmax>159</xmax>
			<ymin>114</ymin>
			<ymax>193</ymax>
		</bndbox>
	</object>
	<object>
		<name>sebo-crystan-conglo</name>
		<pose>Unspecified</pose>
		<truncated>0</truncated>
		<difficult>0</difficult>
		<occluded>0</occluded>
		<bndbox>
			<xmin>440</xmin>
			<xmax>537</xmax>
			<ymin>124</ymin>
			<ymax>189</ymax>
		</bndbox>
	</object>
	<object>
		<name>purulent</name>
		<pose>Unspecified</pose>
		<truncated>0</truncated>
		<difficult>0</difficult>
		<occluded>0</occluded>
		<bndbox>
			<xmin>721</xmin>
			<xmax>751</xmax>
			<ymin>98</ymin>
			<ymax>130</ymax>
		</bndbox>
	</object>
	<object>
		<name>purulent</name>
		<pose>Unspecified</pose>
		<truncated>0</truncated>
		<difficult>0</difficult>
		<occluded>0</occluded>
		<bndbox>
			<xmin>710</xmin>
			<xmax>751</xmax>
			<ymin>47</ymin>
			<ymax>77</ymax>
		</bndbox>
	</object>
	<object>
		<name>blackhead</name>
		<pose>Unspecified</pose>
		<truncated>0</truncated>
		<difficult>0</difficult>
		<occluded>0</occluded>
		<bndbox>
			<xmin>473</xmin>
			<xmax>511</xmax>
			<ymin>61</ymin>
			<ymax>96</ymax>
		</bndbox>
	</object>
	<object>
		<name>acne_scars</name>
		<pose>Unspecified</pose>
		<truncated>0</truncated>
		<difficult>0</difficult>
		<occluded>0</occluded>
		<bndbox>
			<xmin>1</xmin>
			<xmax>38</xmax>
			<ymin>318</ymin>
			<ymax>422</ymax>
		</bndbox>
	</object>
	<object>
		<name>acne_scars</name>
		<pose>Unspecified</pose>
		<truncated>0</truncated>
		<difficult>0</difficult>
		<occluded>0</occluded>
		<bndbox>
			<xmin>100</xmin>
			<xmax>184</xmax>
			<ymin>546</ymin>
			<ymax>606</ymax>
		</bndbox>
	</object>
	<object>
		<name>acne_scars</name>
		<pose>Unspecified</pose>
		<truncated>0</truncated>
		<difficult>0</difficult>
		<occluded>0</occluded>
		<bndbox>
			<xmin>1</xmin>
			<xmax>68</xmax>
			<ymin>453</ymin>
			<ymax>530</ymax>
		</bndbox>
	</object>
	<object>
		<name>blackhead</name>
		<pose>Unspecified</pose>
		<truncated>0</truncated>
		<difficult>0</difficult>
		<occluded>0</occluded>
		<bndbox>
			<xmin>46</xmin>
			<xmax>118</xmax>
			<ymin>333</ymin>
			<ymax>395</ymax>
		</bndbox>
	</object>
	<object>
		<name>purulent</name>
		<pose>Unspecified</pose>
		<truncated>0</truncated>
		<difficult>0</difficult>
		<occluded>0</occluded>
		<bndbox>
			<xmin>85</xmin>
			<xmax>131</xmax>
			<ymin>300</ymin>
			<ymax>340</ymax>
		</bndbox>
	</object>
	<object>
		<name>purulent</name>
		<pose>Unspecified</pose>
		<truncated>0</truncated>
		<difficult>0</difficult>
		<occluded>0</occluded>
		<bndbox>
			<xmin>512</xmin>
			<xmax>575</xmax>
			<ymin>502</ymin>
			<ymax>585</ymax>
		</bndbox>
	</object>
	<object>
		<name>purulent</name>
		<pose>Unspecified</pose>
		<truncated>0</truncated>
		<difficult>0</difficult>
		<occluded>0</occluded>
		<bndbox>
			<xmin>448</xmin>
			<xmax>504</xmax>
			<ymin>506</ymin>
			<ymax>557</ymax>
		</bndbox>
	</object>
	<object>
		<name>purulent</name>
		<pose>Unspecified</pose>
		<truncated>0</truncated>
		<difficult>0</difficult>
		<occluded>0</occluded>
		<bndbox>
			<xmin>558</xmin>
			<xmax>605</xmax>
			<ymin>370</ymin>
			<ymax>424</ymax>
		</bndbox>
	</object>
	<object>
		<name>acne_scars</name>
		<pose>Unspecified</pose>
		<truncated>0</truncated>
		<difficult>0</difficult>
		<occluded>0</occluded>
		<bndbox>
			<xmin>396</xmin>
			<xmax>461</xmax>
			<ymin>421</ymin>
			<ymax>491</ymax>
		</bndbox>
	</object>
	<object>
		<name>sebo-crystan-conglo</name>
		<pose>Unspecified</pose>
		<truncated>0</truncated>
		<difficult>0</difficult>
		<occluded>0</occluded>
		<bndbox>
			<xmin>494</xmin>
			<xmax>573</xmax>
			<ymin>305</ymin>
			<ymax>382</ymax>
		</bndbox>
	</object>
	<object>
		<name>folliculitis</name>
		<pose>Unspecified</pose>
		<truncated>0</truncated>
		<difficult>0</difficult>
		<occluded>0</occluded>
		<bndbox>
			<xmin>235</xmin>
			<xmax>298</xmax>
			<ymin>391</ymin>
			<ymax>451</ymax>
		</bndbox>
	</object>
	<object>
		<name>papular</name>
		<pose>Unspecified</pose>
		<truncated>0</truncated>
		<difficult>0</difficult>
		<occluded>0</occluded>
		<bndbox>
			<xmin>468</xmin>
			<xmax>510</xmax>
			<ymin>383</ymin>
			<ymax>429</ymax>
		</bndbox>
	</object>
	<object>
		<name>papular</name>
		<pose>Unspecified</pose>
		<truncated>0</truncated>
		<difficult>0</difficult>
		<occluded>0</occluded>
		<bndbox>
			<xmin>636</xmin>
			<xmax>673</xmax>
			<ymin>353</ymin>
			<ymax>390</ymax>
		</bndbox>
	</object>
</annotation>
