<annotation>
	<folder></folder>
	<filename>set2---301-_jpg.rf.910b501672a1de20b275443dc6c81635.jpg</filename>
	<path>set2---301-_jpg.rf.910b501672a1de20b275443dc6c81635.jpg</path>
	<source>
		<database>roboflow.com</database>
	</source>
	<size>
		<width>764</width>
		<height>510</height>
		<depth>3</depth>
	</size>
	<segmented>0</segmented>
	<object>
		<name>papular</name>
		<pose>Unspecified</pose>
		<truncated>0</truncated>
		<difficult>0</difficult>
		<occluded>0</occluded>
		<bndbox>
			<xmin>103</xmin>
			<xmax>156</xmax>
			<ymin>43</ymin>
			<ymax>99</ymax>
		</bndbox>
	</object>
	<object>
		<name>papular</name>
		<pose>Unspecified</pose>
		<truncated>0</truncated>
		<difficult>0</difficult>
		<occluded>0</occluded>
		<bndbox>
			<xmin>138</xmin>
			<xmax>205</xmax>
			<ymin>136</ymin>
			<ymax>199</ymax>
		</bndbox>
	</object>
	<object>
		<name>papular</name>
		<pose>Unspecified</pose>
		<truncated>0</truncated>
		<difficult>0</difficult>
		<occluded>0</occluded>
		<bndbox>
			<xmin>99</xmin>
			<xmax>136</xmax>
			<ymin>164</ymin>
			<ymax>199</ymax>
		</bndbox>
	</object>
	<object>
		<name>papular</name>
		<pose>Unspecified</pose>
		<truncated>0</truncated>
		<difficult>0</difficult>
		<occluded>0</occluded>
		<bndbox>
			<xmin>99</xmin>
			<xmax>146</xmax>
			<ymin>186</ymin>
			<ymax>199</ymax>
		</bndbox>
	</object>
	<object>
		<name>papular</name>
		<pose>Unspecified</pose>
		<truncated>0</truncated>
		<difficult>0</difficult>
		<occluded>0</occluded>
		<bndbox>
			<xmin>538</xmin>
			<xmax>684</xmax>
			<ymin>92</ymin>
			<ymax>130</ymax>
		</bndbox>
	</object>
	<object>
		<name>papular</name>
		<pose>Unspecified</pose>
		<truncated>0</truncated>
		<difficult>0</difficult>
		<occluded>0</occluded>
		<bndbox>
			<xmin>588</xmin>
			<xmax>642</xmax>
			<ymin>148</ymin>
			<ymax>168</ymax>
		</bndbox>
	</object>
	<object>
		<name>papular</name>
		<pose>Unspecified</pose>
		<truncated>0</truncated>
		<difficult>0</difficult>
		<occluded>0</occluded>
		<bndbox>
			<xmin>430</xmin>
			<xmax>519</xmax>
			<ymin>123</ymin>
			<ymax>151</ymax>
		</bndbox>
	</object>
	<object>
		<name>papular</name>
		<pose>Unspecified</pose>
		<truncated>0</truncated>
		<difficult>0</difficult>
		<occluded>0</occluded>
		<bndbox>
			<xmin>352</xmin>
			<xmax>456</xmax>
			<ymin>141</ymin>
			<ymax>172</ymax>
		</bndbox>
	</object>
	<object>
		<name>purulent</name>
		<pose>Unspecified</pose>
		<truncated>0</truncated>
		<difficult>0</difficult>
		<occluded>0</occluded>
		<bndbox>
			<xmin>391</xmin>
			<xmax>449</xmax>
			<ymin>84</ymin>
			<ymax>101</ymax>
		</bndbox>
	</object>
	<object>
		<name>purulent</name>
		<pose>Unspecified</pose>
		<truncated>0</truncated>
		<difficult>0</difficult>
		<occluded>0</occluded>
		<bndbox>
			<xmin>552</xmin>
			<xmax>601</xmax>
			<ymin>6</ymin>
			<ymax>25</ymax>
		</bndbox>
	</object>
	<object>
		<name>blackhead</name>
		<pose>Unspecified</pose>
		<truncated>0</truncated>
		<difficult>0</difficult>
		<occluded>0</occluded>
		<bndbox>
			<xmin>639</xmin>
			<xmax>685</xmax>
			<ymin>12</ymin>
			<ymax>27</ymax>
		</bndbox>
	</object>
	<object>
		<name>blackhead</name>
		<pose>Unspecified</pose>
		<truncated>0</truncated>
		<difficult>0</difficult>
		<occluded>0</occluded>
		<bndbox>
			<xmin>495</xmin>
			<xmax>541</xmax>
			<ymin>20</ymin>
			<ymax>36</ymax>
		</bndbox>
	</object>
	<object>
		<name>blackhead</name>
		<pose>Unspecified</pose>
		<truncated>0</truncated>
		<difficult>0</difficult>
		<occluded>0</occluded>
		<bndbox>
			<xmin>568</xmin>
			<xmax>601</xmax>
			<ymin>48</ymin>
			<ymax>60</ymax>
		</bndbox>
	</object>
	<object>
		<name>blackhead</name>
		<pose>Unspecified</pose>
		<truncated>0</truncated>
		<difficult>0</difficult>
		<occluded>0</occluded>
		<bndbox>
			<xmin>681</xmin>
			<xmax>731</xmax>
			<ymin>25</ymin>
			<ymax>43</ymax>
		</bndbox>
	</object>
	<object>
		<name>blackhead</name>
		<pose>Unspecified</pose>
		<truncated>0</truncated>
		<difficult>0</difficult>
		<occluded>0</occluded>
		<bndbox>
			<xmin>683</xmin>
			<xmax>712</xmax>
			<ymin>50</ymin>
			<ymax>58</ymax>
		</bndbox>
	</object>
	<object>
		<name>blackhead</name>
		<pose>Unspecified</pose>
		<truncated>0</truncated>
		<difficult>0</difficult>
		<occluded>0</occluded>
		<bndbox>
			<xmin>624</xmin>
			<xmax>655</xmax>
			<ymin>133</ymin>
			<ymax>145</ymax>
		</bndbox>
	</object>
	<object>
		<name>blackhead</name>
		<pose>Unspecified</pose>
		<truncated>0</truncated>
		<difficult>0</difficult>
		<occluded>0</occluded>
		<bndbox>
			<xmin>656</xmin>
			<xmax>683</xmax>
			<ymin>123</ymin>
			<ymax>136</ymax>
		</bndbox>
	</object>
	<object>
		<name>papular</name>
		<pose>Unspecified</pose>
		<truncated>0</truncated>
		<difficult>0</difficult>
		<occluded>0</occluded>
		<bndbox>
			<xmin>507</xmin>
			<xmax>588</xmax>
			<ymin>123</ymin>
			<ymax>148</ymax>
		</bndbox>
	</object>
	<object>
		<name>papular</name>
		<pose>Unspecified</pose>
		<truncated>0</truncated>
		<difficult>0</difficult>
		<occluded>0</occluded>
		<bndbox>
			<xmin>655</xmin>
			<xmax>761</xmax>
			<ymin>69</ymin>
			<ymax>103</ymax>
		</bndbox>
	</object>
	<object>
		<name>milium</name>
		<pose>Unspecified</pose>
		<truncated>0</truncated>
		<difficult>0</difficult>
		<occluded>0</occluded>
		<bndbox>
			<xmin>191</xmin>
			<xmax>242</xmax>
			<ymin>424</ymin>
			<ymax>480</ymax>
		</bndbox>
	</object>
	<object>
		<name>milium</name>
		<pose>Unspecified</pose>
		<truncated>0</truncated>
		<difficult>0</difficult>
		<occluded>0</occluded>
		<bndbox>
			<xmin>100</xmin>
			<xmax>155</xmax>
			<ymin>401</ymin>
			<ymax>453</ymax>
		</bndbox>
	</object>
	<object>
		<name>milium</name>
		<pose>Unspecified</pose>
		<truncated>0</truncated>
		<difficult>0</difficult>
		<occluded>0</occluded>
		<bndbox>
			<xmin>1</xmin>
			<xmax>47</xmax>
			<ymin>445</ymin>
			<ymax>511</ymax>
		</bndbox>
	</object>
	<object>
		<name>milium</name>
		<pose>Unspecified</pose>
		<truncated>0</truncated>
		<difficult>0</difficult>
		<occluded>0</occluded>
		<bndbox>
			<xmin>38</xmin>
			<xmax>92</xmax>
			<ymin>285</ymin>
			<ymax>346</ymax>
		</bndbox>
	</object>
	<object>
		<name>whitehead</name>
		<pose>Unspecified</pose>
		<truncated>0</truncated>
		<difficult>0</difficult>
		<occluded>0</occluded>
		<bndbox>
			<xmin>612</xmin>
			<xmax>657</xmax>
			<ymin>324</ymin>
			<ymax>372</ymax>
		</bndbox>
	</object>
	<object>
		<name>whitehead</name>
		<pose>Unspecified</pose>
		<truncated>0</truncated>
		<difficult>0</difficult>
		<occluded>0</occluded>
		<bndbox>
			<xmin>489</xmin>
			<xmax>528</xmax>
			<ymin>344</ymin>
			<ymax>384</ymax>
		</bndbox>
	</object>
	<object>
		<name>blackhead</name>
		<pose>Unspecified</pose>
		<truncated>0</truncated>
		<difficult>0</difficult>
		<occluded>0</occluded>
		<bndbox>
			<xmin>593</xmin>
			<xmax>627</xmax>
			<ymin>285</ymin>
			<ymax>320</ymax>
		</bndbox>
	</object>
	<object>
		<name>acne_scars</name>
		<pose>Unspecified</pose>
		<truncated>0</truncated>
		<difficult>0</difficult>
		<occluded>0</occluded>
		<bndbox>
			<xmin>307</xmin>
			<xmax>359</xmax>
			<ymin>326</ymin>
			<ymax>384</ymax>
		</bndbox>
	</object>
	<object>
		<name>acne_scars</name>
		<pose>Unspecified</pose>
		<truncated>0</truncated>
		<difficult>0</difficult>
		<occluded>0</occluded>
		<bndbox>
			<xmin>396</xmin>
			<xmax>443</xmax>
			<ymin>363</ymin>
			<ymax>408</ymax>
		</bndbox>
	</object>
	<object>
		<name>acne_scars</name>
		<pose>Unspecified</pose>
		<truncated>0</truncated>
		<difficult>0</difficult>
		<occluded>0</occluded>
		<bndbox>
			<xmin>333</xmin>
			<xmax>380</xmax>
			<ymin>363</ymin>
			<ymax>419</ymax>
		</bndbox>
	</object>
	<object>
		<name>acne_scars</name>
		<pose>Unspecified</pose>
		<truncated>0</truncated>
		<difficult>0</difficult>
		<occluded>0</occluded>
		<bndbox>
			<xmin>486</xmin>
			<xmax>531</xmax>
			<ymin>420</ymin>
			<ymax>465</ymax>
		</bndbox>
	</object>
	<object>
		<name>acne_scars</name>
		<pose>Unspecified</pose>
		<truncated>0</truncated>
		<difficult>0</difficult>
		<occluded>0</occluded>
		<bndbox>
			<xmin>597</xmin>
			<xmax>647</xmax>
			<ymin>419</ymin>
			<ymax>466</ymax>
		</bndbox>
	</object>
</annotation>
