<annotation>
	<folder></folder>
	<filename>set2---124-_jpg.rf.810e3bd8e511f73bcfd123bd909a0ce8.jpg</filename>
	<path>set2---124-_jpg.rf.810e3bd8e511f73bcfd123bd909a0ce8.jpg</path>
	<source>
		<database>roboflow.com</database>
	</source>
	<size>
		<width>826</width>
		<height>800</height>
		<depth>3</depth>
	</size>
	<segmented>0</segmented>
	<object>
		<name>whitehead</name>
		<pose>Unspecified</pose>
		<truncated>0</truncated>
		<difficult>0</difficult>
		<occluded>0</occluded>
		<bndbox>
			<xmin>53</xmin>
			<xmax>110</xmax>
			<ymin>309</ymin>
			<ymax>368</ymax>
		</bndbox>
	</object>
	<object>
		<name>papular</name>
		<pose>Unspecified</pose>
		<truncated>0</truncated>
		<difficult>0</difficult>
		<occluded>0</occluded>
		<bndbox>
			<xmin>1</xmin>
			<xmax>49</xmax>
			<ymin>1</ymin>
			<ymax>41</ymax>
		</bndbox>
	</object>
	<object>
		<name>papular</name>
		<pose>Unspecified</pose>
		<truncated>0</truncated>
		<difficult>0</difficult>
		<occluded>0</occluded>
		<bndbox>
			<xmin>139</xmin>
			<xmax>218</xmax>
			<ymin>41</ymin>
			<ymax>115</ymax>
		</bndbox>
	</object>
	<object>
		<name>papular</name>
		<pose>Unspecified</pose>
		<truncated>0</truncated>
		<difficult>0</difficult>
		<occluded>0</occluded>
		<bndbox>
			<xmin>226</xmin>
			<xmax>292</xmax>
			<ymin>288</ymin>
			<ymax>381</ymax>
		</bndbox>
	</object>
	<object>
		<name>papular</name>
		<pose>Unspecified</pose>
		<truncated>0</truncated>
		<difficult>0</difficult>
		<occluded>0</occluded>
		<bndbox>
			<xmin>1</xmin>
			<xmax>57</xmax>
			<ymin>133</ymin>
			<ymax>216</ymax>
		</bndbox>
	</object>
	<object>
		<name>papular</name>
		<pose>Unspecified</pose>
		<truncated>0</truncated>
		<difficult>0</difficult>
		<occluded>0</occluded>
		<bndbox>
			<xmin>46</xmin>
			<xmax>119</xmax>
			<ymin>1</ymin>
			<ymax>65</ymax>
		</bndbox>
	</object>
	<object>
		<name>papular</name>
		<pose>Unspecified</pose>
		<truncated>0</truncated>
		<difficult>0</difficult>
		<occluded>0</occluded>
		<bndbox>
			<xmin>146</xmin>
			<xmax>231</xmax>
			<ymin>144</ymin>
			<ymax>234</ymax>
		</bndbox>
	</object>
	<object>
		<name>papular</name>
		<pose>Unspecified</pose>
		<truncated>0</truncated>
		<difficult>0</difficult>
		<occluded>0</occluded>
		<bndbox>
			<xmin>1</xmin>
			<xmax>28</xmax>
			<ymin>310</ymin>
			<ymax>378</ymax>
		</bndbox>
	</object>
	<object>
		<name>acne_scars</name>
		<pose>Unspecified</pose>
		<truncated>0</truncated>
		<difficult>0</difficult>
		<occluded>0</occluded>
		<bndbox>
			<xmin>786</xmin>
			<xmax>827</xmax>
			<ymin>15</ymin>
			<ymax>129</ymax>
		</bndbox>
	</object>
	<object>
		<name>acne_scars</name>
		<pose>Unspecified</pose>
		<truncated>0</truncated>
		<difficult>0</difficult>
		<occluded>0</occluded>
		<bndbox>
			<xmin>563</xmin>
			<xmax>638</xmax>
			<ymin>24</ymin>
			<ymax>106</ymax>
		</bndbox>
	</object>
	<object>
		<name>acne_scars</name>
		<pose>Unspecified</pose>
		<truncated>0</truncated>
		<difficult>0</difficult>
		<occluded>0</occluded>
		<bndbox>
			<xmin>781</xmin>
			<xmax>827</xmax>
			<ymin>199</ymin>
			<ymax>327</ymax>
		</bndbox>
	</object>
	<object>
		<name>keloid</name>
		<pose>Unspecified</pose>
		<truncated>0</truncated>
		<difficult>0</difficult>
		<occluded>0</occluded>
		<bndbox>
			<xmin>634</xmin>
			<xmax>758</xmax>
			<ymin>256</ymin>
			<ymax>405</ymax>
		</bndbox>
	</object>
	<object>
		<name>sebo-crystan-conglo</name>
		<pose>Unspecified</pose>
		<truncated>0</truncated>
		<difficult>0</difficult>
		<occluded>0</occluded>
		<bndbox>
			<xmin>158</xmin>
			<xmax>206</xmax>
			<ymin>466</ymin>
			<ymax>494</ymax>
		</bndbox>
	</object>
	<object>
		<name>sebo-crystan-conglo</name>
		<pose>Unspecified</pose>
		<truncated>0</truncated>
		<difficult>0</difficult>
		<occluded>0</occluded>
		<bndbox>
			<xmin>134</xmin>
			<xmax>177</xmax>
			<ymin>493</ymin>
			<ymax>521</ymax>
		</bndbox>
	</object>
	<object>
		<name>purulent</name>
		<pose>Unspecified</pose>
		<truncated>0</truncated>
		<difficult>0</difficult>
		<occluded>0</occluded>
		<bndbox>
			<xmin>26</xmin>
			<xmax>66</xmax>
			<ymin>658</ymin>
			<ymax>696</ymax>
		</bndbox>
	</object>
	<object>
		<name>purulent</name>
		<pose>Unspecified</pose>
		<truncated>0</truncated>
		<difficult>0</difficult>
		<occluded>0</occluded>
		<bndbox>
			<xmin>185</xmin>
			<xmax>227</xmax>
			<ymin>562</ymin>
			<ymax>592</ymax>
		</bndbox>
	</object>
	<object>
		<name>purulent</name>
		<pose>Unspecified</pose>
		<truncated>0</truncated>
		<difficult>0</difficult>
		<occluded>0</occluded>
		<bndbox>
			<xmin>179</xmin>
			<xmax>220</xmax>
			<ymin>616</ymin>
			<ymax>654</ymax>
		</bndbox>
	</object>
	<object>
		<name>papular</name>
		<pose>Unspecified</pose>
		<truncated>0</truncated>
		<difficult>0</difficult>
		<occluded>0</occluded>
		<bndbox>
			<xmin>55</xmin>
			<xmax>107</xmax>
			<ymin>552</ymin>
			<ymax>597</ymax>
		</bndbox>
	</object>
	<object>
		<name>papular</name>
		<pose>Unspecified</pose>
		<truncated>0</truncated>
		<difficult>0</difficult>
		<occluded>0</occluded>
		<bndbox>
			<xmin>138</xmin>
			<xmax>186</xmax>
			<ymin>621</ymin>
			<ymax>666</ymax>
		</bndbox>
	</object>
	<object>
		<name>papular</name>
		<pose>Unspecified</pose>
		<truncated>0</truncated>
		<difficult>0</difficult>
		<occluded>0</occluded>
		<bndbox>
			<xmin>171</xmin>
			<xmax>219</xmax>
			<ymin>525</ymin>
			<ymax>559</ymax>
		</bndbox>
	</object>
	<object>
		<name>purulent</name>
		<pose>Unspecified</pose>
		<truncated>0</truncated>
		<difficult>0</difficult>
		<occluded>0</occluded>
		<bndbox>
			<xmin>644</xmin>
			<xmax>733</xmax>
			<ymin>417</ymin>
			<ymax>453</ymax>
		</bndbox>
	</object>
	<object>
		<name>purulent</name>
		<pose>Unspecified</pose>
		<truncated>0</truncated>
		<difficult>0</difficult>
		<occluded>0</occluded>
		<bndbox>
			<xmin>550</xmin>
			<xmax>642</xmax>
			<ymin>689</ymin>
			<ymax>746</ymax>
		</bndbox>
	</object>
	<object>
		<name>sebo-crystan-conglo</name>
		<pose>Unspecified</pose>
		<truncated>0</truncated>
		<difficult>0</difficult>
		<occluded>0</occluded>
		<bndbox>
			<xmin>659</xmin>
			<xmax>773</xmax>
			<ymin>716</ymin>
			<ymax>787</ymax>
		</bndbox>
	</object>
</annotation>
