<annotation>
	<folder></folder>
	<filename>syringoma_--155-_jpg.rf.e3cef8d66b1819202a49a4122e3568d4.jpg</filename>
	<path>syringoma_--155-_jpg.rf.e3cef8d66b1819202a49a4122e3568d4.jpg</path>
	<source>
		<database>roboflow.com</database>
	</source>
	<size>
		<width>1280</width>
		<height>720</height>
		<depth>3</depth>
	</size>
	<segmented>0</segmented>
	<object>
		<name>syringoma</name>
		<pose>Unspecified</pose>
		<truncated>0</truncated>
		<difficult>0</difficult>
		<occluded>0</occluded>
		<bndbox>
			<xmin>344</xmin>
			<xmax>453</xmax>
			<ymin>1</ymin>
			<ymax>115</ymax>
		</bndbox>
	</object>
	<object>
		<name>sebo-crystan-conglo</name>
		<pose>Unspecified</pose>
		<truncated>0</truncated>
		<difficult>0</difficult>
		<occluded>0</occluded>
		<bndbox>
			<xmin>892</xmin>
			<xmax>970</xmax>
			<ymin>101</ymin>
			<ymax>125</ymax>
		</bndbox>
	</object>
	<object>
		<name>sebo-crystan-conglo</name>
		<pose>Unspecified</pose>
		<truncated>0</truncated>
		<difficult>0</difficult>
		<occluded>0</occluded>
		<bndbox>
			<xmin>841</xmin>
			<xmax>948</xmax>
			<ymin>64</ymin>
			<ymax>100</ymax>
		</bndbox>
	</object>
	<object>
		<name>sebo-crystan-conglo</name>
		<pose>Unspecified</pose>
		<truncated>0</truncated>
		<difficult>0</difficult>
		<occluded>0</occluded>
		<bndbox>
			<xmin>673</xmin>
			<xmax>788</xmax>
			<ymin>153</ymin>
			<ymax>196</ymax>
		</bndbox>
	</object>
	<object>
		<name>sebo-crystan-conglo</name>
		<pose>Unspecified</pose>
		<truncated>0</truncated>
		<difficult>0</difficult>
		<occluded>0</occluded>
		<bndbox>
			<xmin>984</xmin>
			<xmax>1097</xmax>
			<ymin>103</ymin>
			<ymax>133</ymax>
		</bndbox>
	</object>
	<object>
		<name>sebo-crystan-conglo</name>
		<pose>Unspecified</pose>
		<truncated>0</truncated>
		<difficult>0</difficult>
		<occluded>0</occluded>
		<bndbox>
			<xmin>793</xmin>
			<xmax>886</xmax>
			<ymin>103</ymin>
			<ymax>129</ymax>
		</bndbox>
	</object>
	<object>
		<name>purulent</name>
		<pose>Unspecified</pose>
		<truncated>0</truncated>
		<difficult>0</difficult>
		<occluded>0</occluded>
		<bndbox>
			<xmin>726</xmin>
			<xmax>800</xmax>
			<ymin>72</ymin>
			<ymax>96</ymax>
		</bndbox>
	</object>
	<object>
		<name>purulent</name>
		<pose>Unspecified</pose>
		<truncated>0</truncated>
		<difficult>0</difficult>
		<occluded>0</occluded>
		<bndbox>
			<xmin>942</xmin>
			<xmax>1003</xmax>
			<ymin>90</ymin>
			<ymax>112</ymax>
		</bndbox>
	</object>
	<object>
		<name>whitehead</name>
		<pose>Unspecified</pose>
		<truncated>0</truncated>
		<difficult>0</difficult>
		<occluded>0</occluded>
		<bndbox>
			<xmin>1</xmin>
			<xmax>189</xmax>
			<ymin>461</ymin>
			<ymax>669</ymax>
		</bndbox>
	</object>
	<object>
		<name>whitehead</name>
		<pose>Unspecified</pose>
		<truncated>0</truncated>
		<difficult>0</difficult>
		<occluded>0</occluded>
		<bndbox>
			<xmin>123</xmin>
			<xmax>337</xmax>
			<ymin>241</ymin>
			<ymax>535</ymax>
		</bndbox>
	</object>
	<object>
		<name>whitehead</name>
		<pose>Unspecified</pose>
		<truncated>0</truncated>
		<difficult>0</difficult>
		<occluded>0</occluded>
		<bndbox>
			<xmin>593</xmin>
			<xmax>763</xmax>
			<ymin>306</ymin>
			<ymax>421</ymax>
		</bndbox>
	</object>
	<object>
		<name>whitehead</name>
		<pose>Unspecified</pose>
		<truncated>0</truncated>
		<difficult>0</difficult>
		<occluded>0</occluded>
		<bndbox>
			<xmin>949</xmin>
			<xmax>1119</xmax>
			<ymin>275</ymin>
			<ymax>383</ymax>
		</bndbox>
	</object>
	<object>
		<name>whitehead</name>
		<pose>Unspecified</pose>
		<truncated>0</truncated>
		<difficult>0</difficult>
		<occluded>0</occluded>
		<bndbox>
			<xmin>963</xmin>
			<xmax>1098</xmax>
			<ymin>546</ymin>
			<ymax>639</ymax>
		</bndbox>
	</object>
	<object>
		<name>whitehead</name>
		<pose>Unspecified</pose>
		<truncated>0</truncated>
		<difficult>0</difficult>
		<occluded>0</occluded>
		<bndbox>
			<xmin>1032</xmin>
			<xmax>1195</xmax>
			<ymin>479</ymin>
			<ymax>577</ymax>
		</bndbox>
	</object>
	<object>
		<name>whitehead</name>
		<pose>Unspecified</pose>
		<truncated>0</truncated>
		<difficult>0</difficult>
		<occluded>0</occluded>
		<bndbox>
			<xmin>1015</xmin>
			<xmax>1146</xmax>
			<ymin>621</ymin>
			<ymax>721</ymax>
		</bndbox>
	</object>
	<object>
		<name>sebo-crystan-conglo</name>
		<pose>Unspecified</pose>
		<truncated>0</truncated>
		<difficult>0</difficult>
		<occluded>0</occluded>
		<bndbox>
			<xmin>730</xmin>
			<xmax>885</xmax>
			<ymin>432</ymin>
			<ymax>553</ymax>
		</bndbox>
	</object>
</annotation>
