<annotation>
	<folder></folder>
	<filename>syringoma_--17-_jpg.rf.9cf97f964d0c90a45a7c2c2fbbec44f2.jpg</filename>
	<path>syringoma_--17-_jpg.rf.9cf97f964d0c90a45a7c2c2fbbec44f2.jpg</path>
	<source>
		<database>roboflow.com</database>
	</source>
	<size>
		<width>1280</width>
		<height>1706</height>
		<depth>3</depth>
	</size>
	<segmented>0</segmented>
	<object>
		<name>purulent</name>
		<pose>Unspecified</pose>
		<truncated>0</truncated>
		<difficult>0</difficult>
		<occluded>0</occluded>
		<bndbox>
			<xmin>1098</xmin>
			<xmax>1166</xmax>
			<ymin>176</ymin>
			<ymax>247</ymax>
		</bndbox>
	</object>
	<object>
		<name>purulent</name>
		<pose>Unspecified</pose>
		<truncated>0</truncated>
		<difficult>0</difficult>
		<occluded>0</occluded>
		<bndbox>
			<xmin>873</xmin>
			<xmax>936</xmax>
			<ymin>217</ymin>
			<ymax>294</ymax>
		</bndbox>
	</object>
	<object>
		<name>purulent</name>
		<pose>Unspecified</pose>
		<truncated>0</truncated>
		<difficult>0</difficult>
		<occluded>0</occluded>
		<bndbox>
			<xmin>1154</xmin>
			<xmax>1203</xmax>
			<ymin>568</ymin>
			<ymax>626</ymax>
		</bndbox>
	</object>
	<object>
		<name>whitehead</name>
		<pose>Unspecified</pose>
		<truncated>0</truncated>
		<difficult>0</difficult>
		<occluded>0</occluded>
		<bndbox>
			<xmin>731</xmin>
			<xmax>786</xmax>
			<ymin>302</ymin>
			<ymax>379</ymax>
		</bndbox>
	</object>
	<object>
		<name>whitehead</name>
		<pose>Unspecified</pose>
		<truncated>0</truncated>
		<difficult>0</difficult>
		<occluded>0</occluded>
		<bndbox>
			<xmin>824</xmin>
			<xmax>878</xmax>
			<ymin>464</ymin>
			<ymax>525</ymax>
		</bndbox>
	</object>
	<object>
		<name>whitehead</name>
		<pose>Unspecified</pose>
		<truncated>0</truncated>
		<difficult>0</difficult>
		<occluded>0</occluded>
		<bndbox>
			<xmin>847</xmin>
			<xmax>887</xmax>
			<ymin>572</ymin>
			<ymax>635</ymax>
		</bndbox>
	</object>
	<object>
		<name>papular</name>
		<pose>Unspecified</pose>
		<truncated>0</truncated>
		<difficult>0</difficult>
		<occluded>0</occluded>
		<bndbox>
			<xmin>897</xmin>
			<xmax>950</xmax>
			<ymin>418</ymin>
			<ymax>480</ymax>
		</bndbox>
	</object>
	<object>
		<name>papular</name>
		<pose>Unspecified</pose>
		<truncated>0</truncated>
		<difficult>0</difficult>
		<occluded>0</occluded>
		<bndbox>
			<xmin>1004</xmin>
			<xmax>1066</xmax>
			<ymin>659</ymin>
			<ymax>766</ymax>
		</bndbox>
	</object>
	<object>
		<name>papular</name>
		<pose>Unspecified</pose>
		<truncated>0</truncated>
		<difficult>0</difficult>
		<occluded>0</occluded>
		<bndbox>
			<xmin>1020</xmin>
			<xmax>1067</xmax>
			<ymin>298</ymin>
			<ymax>378</ymax>
		</bndbox>
	</object>
	<object>
		<name>papular</name>
		<pose>Unspecified</pose>
		<truncated>0</truncated>
		<difficult>0</difficult>
		<occluded>0</occluded>
		<bndbox>
			<xmin>1099</xmin>
			<xmax>1140</xmax>
			<ymin>539</ymin>
			<ymax>614</ymax>
		</bndbox>
	</object>
	<object>
		<name>purulent</name>
		<pose>Unspecified</pose>
		<truncated>0</truncated>
		<difficult>0</difficult>
		<occluded>0</occluded>
		<bndbox>
			<xmin>167</xmin>
			<xmax>196</xmax>
			<ymin>1204</ymin>
			<ymax>1258</ymax>
		</bndbox>
	</object>
	<object>
		<name>whitehead</name>
		<pose>Unspecified</pose>
		<truncated>0</truncated>
		<difficult>0</difficult>
		<occluded>0</occluded>
		<bndbox>
			<xmin>209</xmin>
			<xmax>245</xmax>
			<ymin>1142</ymin>
			<ymax>1199</ymax>
		</bndbox>
	</object>
	<object>
		<name>whitehead</name>
		<pose>Unspecified</pose>
		<truncated>0</truncated>
		<difficult>0</difficult>
		<occluded>0</occluded>
		<bndbox>
			<xmin>197</xmin>
			<xmax>220</xmax>
			<ymin>1278</ymin>
			<ymax>1321</ymax>
		</bndbox>
	</object>
	<object>
		<name>whitehead</name>
		<pose>Unspecified</pose>
		<truncated>0</truncated>
		<difficult>0</difficult>
		<occluded>0</occluded>
		<bndbox>
			<xmin>282</xmin>
			<xmax>304</xmax>
			<ymin>1293</ymin>
			<ymax>1325</ymax>
		</bndbox>
	</object>
	<object>
		<name>whitehead</name>
		<pose>Unspecified</pose>
		<truncated>0</truncated>
		<difficult>0</difficult>
		<occluded>0</occluded>
		<bndbox>
			<xmin>263</xmin>
			<xmax>286</xmax>
			<ymin>1378</ymin>
			<ymax>1419</ymax>
		</bndbox>
	</object>
	<object>
		<name>whitehead</name>
		<pose>Unspecified</pose>
		<truncated>0</truncated>
		<difficult>0</difficult>
		<occluded>0</occluded>
		<bndbox>
			<xmin>115</xmin>
			<xmax>144</xmax>
			<ymin>1033</ymin>
			<ymax>1086</ymax>
		</bndbox>
	</object>
	<object>
		<name>papular</name>
		<pose>Unspecified</pose>
		<truncated>0</truncated>
		<difficult>0</difficult>
		<occluded>0</occluded>
		<bndbox>
			<xmin>131</xmin>
			<xmax>159</xmax>
			<ymin>1184</ymin>
			<ymax>1223</ymax>
		</bndbox>
	</object>
	<object>
		<name>papular</name>
		<pose>Unspecified</pose>
		<truncated>0</truncated>
		<difficult>0</difficult>
		<occluded>0</occluded>
		<bndbox>
			<xmin>364</xmin>
			<xmax>395</xmax>
			<ymin>1178</ymin>
			<ymax>1230</ymax>
		</bndbox>
	</object>
	<object>
		<name>whitehead</name>
		<pose>Unspecified</pose>
		<truncated>0</truncated>
		<difficult>0</difficult>
		<occluded>0</occluded>
		<bndbox>
			<xmin>998</xmin>
			<xmax>1096</xmax>
			<ymin>1254</ymin>
			<ymax>1315</ymax>
		</bndbox>
	</object>
	<object>
		<name>whitehead</name>
		<pose>Unspecified</pose>
		<truncated>0</truncated>
		<difficult>0</difficult>
		<occluded>0</occluded>
		<bndbox>
			<xmin>1038</xmin>
			<xmax>1155</xmax>
			<ymin>1134</ymin>
			<ymax>1222</ymax>
		</bndbox>
	</object>
	<object>
		<name>whitehead</name>
		<pose>Unspecified</pose>
		<truncated>0</truncated>
		<difficult>0</difficult>
		<occluded>0</occluded>
		<bndbox>
			<xmin>923</xmin>
			<xmax>995</xmax>
			<ymin>1173</ymin>
			<ymax>1230</ymax>
		</bndbox>
	</object>
	<object>
		<name>whitehead</name>
		<pose>Unspecified</pose>
		<truncated>0</truncated>
		<difficult>0</difficult>
		<occluded>0</occluded>
		<bndbox>
			<xmin>922</xmin>
			<xmax>994</xmax>
			<ymin>1120</ymin>
			<ymax>1166</ymax>
		</bndbox>
	</object>
	<object>
		<name>whitehead</name>
		<pose>Unspecified</pose>
		<truncated>0</truncated>
		<difficult>0</difficult>
		<occluded>0</occluded>
		<bndbox>
			<xmin>981</xmin>
			<xmax>1092</xmax>
			<ymin>959</ymin>
			<ymax>1024</ymax>
		</bndbox>
	</object>
	<object>
		<name>whitehead</name>
		<pose>Unspecified</pose>
		<truncated>0</truncated>
		<difficult>0</difficult>
		<occluded>0</occluded>
		<bndbox>
			<xmin>795</xmin>
			<xmax>906</xmax>
			<ymin>1077</ymin>
			<ymax>1147</ymax>
		</bndbox>
	</object>
	<object>
		<name>whitehead</name>
		<pose>Unspecified</pose>
		<truncated>0</truncated>
		<difficult>0</difficult>
		<occluded>0</occluded>
		<bndbox>
			<xmin>530</xmin>
			<xmax>635</xmax>
			<ymin>1160</ymin>
			<ymax>1226</ymax>
		</bndbox>
	</object>
	<object>
		<name>whitehead</name>
		<pose>Unspecified</pose>
		<truncated>0</truncated>
		<difficult>0</difficult>
		<occluded>0</occluded>
		<bndbox>
			<xmin>491</xmin>
			<xmax>565</xmax>
			<ymin>945</ymin>
			<ymax>1011</ymax>
		</bndbox>
	</object>
	<object>
		<name>whitehead</name>
		<pose>Unspecified</pose>
		<truncated>0</truncated>
		<difficult>0</difficult>
		<occluded>0</occluded>
		<bndbox>
			<xmin>564</xmin>
			<xmax>638</xmax>
			<ymin>1614</ymin>
			<ymax>1687</ymax>
		</bndbox>
	</object>
	<object>
		<name>whitehead</name>
		<pose>Unspecified</pose>
		<truncated>0</truncated>
		<difficult>0</difficult>
		<occluded>0</occluded>
		<bndbox>
			<xmin>685</xmin>
			<xmax>796</xmax>
			<ymin>1594</ymin>
			<ymax>1697</ymax>
		</bndbox>
	</object>
	<object>
		<name>whitehead</name>
		<pose>Unspecified</pose>
		<truncated>0</truncated>
		<difficult>0</difficult>
		<occluded>0</occluded>
		<bndbox>
			<xmin>611</xmin>
			<xmax>722</xmax>
			<ymin>1504</ymin>
			<ymax>1565</ymax>
		</bndbox>
	</object>
	<object>
		<name>whitehead</name>
		<pose>Unspecified</pose>
		<truncated>0</truncated>
		<difficult>0</difficult>
		<occluded>0</occluded>
		<bndbox>
			<xmin>931</xmin>
			<xmax>1061</xmax>
			<ymin>1355</ymin>
			<ymax>1454</ymax>
		</bndbox>
	</object>
</annotation>
