<annotation>
	<folder></folder>
	<filename>white_head_--8-_jpg.rf.db295105455387ff5694fa10690ec967.jpg</filename>
	<path>white_head_--8-_jpg.rf.db295105455387ff5694fa10690ec967.jpg</path>
	<source>
		<database>roboflow.com</database>
	</source>
	<size>
		<width>1280</width>
		<height>1706</height>
		<depth>3</depth>
	</size>
	<segmented>0</segmented>
	<object>
		<name>whitehead</name>
		<pose>Unspecified</pose>
		<truncated>0</truncated>
		<difficult>0</difficult>
		<occluded>0</occluded>
		<bndbox>
			<xmin>169</xmin>
			<xmax>260</xmax>
			<ymin>451</ymin>
			<ymax>544</ymax>
		</bndbox>
	</object>
	<object>
		<name>whitehead</name>
		<pose>Unspecified</pose>
		<truncated>0</truncated>
		<difficult>0</difficult>
		<occluded>0</occluded>
		<bndbox>
			<xmin>209</xmin>
			<xmax>311</xmax>
			<ymin>674</ymin>
			<ymax>717</ymax>
		</bndbox>
	</object>
	<object>
		<name>whitehead</name>
		<pose>Unspecified</pose>
		<truncated>0</truncated>
		<difficult>0</difficult>
		<occluded>0</occluded>
		<bndbox>
			<xmin>375</xmin>
			<xmax>522</xmax>
			<ymin>128</ymin>
			<ymax>239</ymax>
		</bndbox>
	</object>
	<object>
		<name>whitehead</name>
		<pose>Unspecified</pose>
		<truncated>0</truncated>
		<difficult>0</difficult>
		<occluded>0</occluded>
		<bndbox>
			<xmin>42</xmin>
			<xmax>205</xmax>
			<ymin>296</ymin>
			<ymax>422</ymax>
		</bndbox>
	</object>
	<object>
		<name>whitehead</name>
		<pose>Unspecified</pose>
		<truncated>0</truncated>
		<difficult>0</difficult>
		<occluded>0</occluded>
		<bndbox>
			<xmin>533</xmin>
			<xmax>669</xmax>
			<ymin>550</ymin>
			<ymax>658</ymax>
		</bndbox>
	</object>
	<object>
		<name>whitehead</name>
		<pose>Unspecified</pose>
		<truncated>0</truncated>
		<difficult>0</difficult>
		<occluded>0</occluded>
		<bndbox>
			<xmin>373</xmin>
			<xmax>463</xmax>
			<ymin>321</ymin>
			<ymax>411</ymax>
		</bndbox>
	</object>
	<object>
		<name>whitehead</name>
		<pose>Unspecified</pose>
		<truncated>0</truncated>
		<difficult>0</difficult>
		<occluded>0</occluded>
		<bndbox>
			<xmin>1167</xmin>
			<xmax>1281</xmax>
			<ymin>279</ymin>
			<ymax>443</ymax>
		</bndbox>
	</object>
	<object>
		<name>flat_wart</name>
		<pose>Unspecified</pose>
		<truncated>0</truncated>
		<difficult>0</difficult>
		<occluded>0</occluded>
		<bndbox>
			<xmin>1213</xmin>
			<xmax>1281</xmax>
			<ymin>1</ymin>
			<ymax>187</ymax>
		</bndbox>
	</object>
	<object>
		<name>purulent</name>
		<pose>Unspecified</pose>
		<truncated>0</truncated>
		<difficult>0</difficult>
		<occluded>0</occluded>
		<bndbox>
			<xmin>388</xmin>
			<xmax>488</xmax>
			<ymin>1224</ymin>
			<ymax>1378</ymax>
		</bndbox>
	</object>
	<object>
		<name>whitehead</name>
		<pose>Unspecified</pose>
		<truncated>0</truncated>
		<difficult>0</difficult>
		<occluded>0</occluded>
		<bndbox>
			<xmin>624</xmin>
			<xmax>700</xmax>
			<ymin>1208</ymin>
			<ymax>1321</ymax>
		</bndbox>
	</object>
	<object>
		<name>whitehead</name>
		<pose>Unspecified</pose>
		<truncated>0</truncated>
		<difficult>0</difficult>
		<occluded>0</occluded>
		<bndbox>
			<xmin>521</xmin>
			<xmax>594</xmax>
			<ymin>772</ymin>
			<ymax>883</ymax>
		</bndbox>
	</object>
	<object>
		<name>whitehead</name>
		<pose>Unspecified</pose>
		<truncated>0</truncated>
		<difficult>0</difficult>
		<occluded>0</occluded>
		<bndbox>
			<xmin>588</xmin>
			<xmax>626</xmax>
			<ymin>1077</ymin>
			<ymax>1140</ymax>
		</bndbox>
	</object>
	<object>
		<name>whitehead</name>
		<pose>Unspecified</pose>
		<truncated>0</truncated>
		<difficult>0</difficult>
		<occluded>0</occluded>
		<bndbox>
			<xmin>190</xmin>
			<xmax>236</xmax>
			<ymin>1069</ymin>
			<ymax>1143</ymax>
		</bndbox>
	</object>
	<object>
		<name>whitehead</name>
		<pose>Unspecified</pose>
		<truncated>0</truncated>
		<difficult>0</difficult>
		<occluded>0</occluded>
		<bndbox>
			<xmin>197</xmin>
			<xmax>243</xmax>
			<ymin>1202</ymin>
			<ymax>1274</ymax>
		</bndbox>
	</object>
	<object>
		<name>whitehead</name>
		<pose>Unspecified</pose>
		<truncated>0</truncated>
		<difficult>0</difficult>
		<occluded>0</occluded>
		<bndbox>
			<xmin>195</xmin>
			<xmax>232</xmax>
			<ymin>1299</ymin>
			<ymax>1363</ymax>
		</bndbox>
	</object>
	<object>
		<name>whitehead</name>
		<pose>Unspecified</pose>
		<truncated>0</truncated>
		<difficult>0</difficult>
		<occluded>0</occluded>
		<bndbox>
			<xmin>31</xmin>
			<xmax>94</xmax>
			<ymin>1149</ymin>
			<ymax>1244</ymax>
		</bndbox>
	</object>
	<object>
		<name>whitehead</name>
		<pose>Unspecified</pose>
		<truncated>0</truncated>
		<difficult>0</difficult>
		<occluded>0</occluded>
		<bndbox>
			<xmin>496</xmin>
			<xmax>536</xmax>
			<ymin>1114</ymin>
			<ymax>1166</ymax>
		</bndbox>
	</object>
	<object>
		<name>whitehead</name>
		<pose>Unspecified</pose>
		<truncated>0</truncated>
		<difficult>0</difficult>
		<occluded>0</occluded>
		<bndbox>
			<xmin>469</xmin>
			<xmax>515</xmax>
			<ymin>1161</ymin>
			<ymax>1230</ymax>
		</bndbox>
	</object>
	<object>
		<name>whitehead</name>
		<pose>Unspecified</pose>
		<truncated>0</truncated>
		<difficult>0</difficult>
		<occluded>0</occluded>
		<bndbox>
			<xmin>359</xmin>
			<xmax>396</xmax>
			<ymin>1324</ymin>
			<ymax>1391</ymax>
		</bndbox>
	</object>
	<object>
		<name>whitehead</name>
		<pose>Unspecified</pose>
		<truncated>0</truncated>
		<difficult>0</difficult>
		<occluded>0</occluded>
		<bndbox>
			<xmin>356</xmin>
			<xmax>393</xmax>
			<ymin>1250</ymin>
			<ymax>1324</ymax>
		</bndbox>
	</object>
	<object>
		<name>whitehead</name>
		<pose>Unspecified</pose>
		<truncated>0</truncated>
		<difficult>0</difficult>
		<occluded>0</occluded>
		<bndbox>
			<xmin>389</xmin>
			<xmax>445</xmax>
			<ymin>1062</ymin>
			<ymax>1163</ymax>
		</bndbox>
	</object>
	<object>
		<name>whitehead</name>
		<pose>Unspecified</pose>
		<truncated>0</truncated>
		<difficult>0</difficult>
		<occluded>0</occluded>
		<bndbox>
			<xmin>362</xmin>
			<xmax>432</xmax>
			<ymin>834</ymin>
			<ymax>918</ymax>
		</bndbox>
	</object>
	<object>
		<name>whitehead</name>
		<pose>Unspecified</pose>
		<truncated>0</truncated>
		<difficult>0</difficult>
		<occluded>0</occluded>
		<bndbox>
			<xmin>235</xmin>
			<xmax>309</xmax>
			<ymin>1416</ymin>
			<ymax>1525</ymax>
		</bndbox>
	</object>
	<object>
		<name>whitehead</name>
		<pose>Unspecified</pose>
		<truncated>0</truncated>
		<difficult>0</difficult>
		<occluded>0</occluded>
		<bndbox>
			<xmin>476</xmin>
			<xmax>527</xmax>
			<ymin>1362</ymin>
			<ymax>1431</ymax>
		</bndbox>
	</object>
	<object>
		<name>whitehead</name>
		<pose>Unspecified</pose>
		<truncated>0</truncated>
		<difficult>0</difficult>
		<occluded>0</occluded>
		<bndbox>
			<xmin>456</xmin>
			<xmax>504</xmax>
			<ymin>1493</ymin>
			<ymax>1573</ymax>
		</bndbox>
	</object>
	<object>
		<name>whitehead</name>
		<pose>Unspecified</pose>
		<truncated>0</truncated>
		<difficult>0</difficult>
		<occluded>0</occluded>
		<bndbox>
			<xmin>332</xmin>
			<xmax>404</xmax>
			<ymin>1433</ymin>
			<ymax>1525</ymax>
		</bndbox>
	</object>
	<object>
		<name>papular</name>
		<pose>Unspecified</pose>
		<truncated>0</truncated>
		<difficult>0</difficult>
		<occluded>0</occluded>
		<bndbox>
			<xmin>293</xmin>
			<xmax>357</xmax>
			<ymin>1297</ymin>
			<ymax>1410</ymax>
		</bndbox>
	</object>
	<object>
		<name>papular</name>
		<pose>Unspecified</pose>
		<truncated>0</truncated>
		<difficult>0</difficult>
		<occluded>0</occluded>
		<bndbox>
			<xmin>215</xmin>
			<xmax>292</xmax>
			<ymin>1230</ymin>
			<ymax>1355</ymax>
		</bndbox>
	</object>
	<object>
		<name>papular</name>
		<pose>Unspecified</pose>
		<truncated>0</truncated>
		<difficult>0</difficult>
		<occluded>0</occluded>
		<bndbox>
			<xmin>117</xmin>
			<xmax>183</xmax>
			<ymin>1064</ymin>
			<ymax>1185</ymax>
		</bndbox>
	</object>
	<object>
		<name>sebo-crystan-conglo</name>
		<pose>Unspecified</pose>
		<truncated>0</truncated>
		<difficult>0</difficult>
		<occluded>0</occluded>
		<bndbox>
			<xmin>440</xmin>
			<xmax>525</xmax>
			<ymin>847</ymin>
			<ymax>954</ymax>
		</bndbox>
	</object>
	<object>
		<name>papular</name>
		<pose>Unspecified</pose>
		<truncated>0</truncated>
		<difficult>0</difficult>
		<occluded>0</occluded>
		<bndbox>
			<xmin>533</xmin>
			<xmax>602</xmax>
			<ymin>1049</ymin>
			<ymax>1154</ymax>
		</bndbox>
	</object>
	<object>
		<name>whitehead</name>
		<pose>Unspecified</pose>
		<truncated>0</truncated>
		<difficult>0</difficult>
		<occluded>0</occluded>
		<bndbox>
			<xmin>371</xmin>
			<xmax>443</xmax>
			<ymin>971</ymin>
			<ymax>1084</ymax>
		</bndbox>
	</object>
	<object>
		<name>whitehead</name>
		<pose>Unspecified</pose>
		<truncated>0</truncated>
		<difficult>0</difficult>
		<occluded>0</occluded>
		<bndbox>
			<xmin>255</xmin>
			<xmax>306</xmax>
			<ymin>1067</ymin>
			<ymax>1138</ymax>
		</bndbox>
	</object>
	<object>
		<name>sebo-crystan-conglo</name>
		<pose>Unspecified</pose>
		<truncated>0</truncated>
		<difficult>0</difficult>
		<occluded>0</occluded>
		<bndbox>
			<xmin>500</xmin>
			<xmax>575</xmax>
			<ymin>887</ymin>
			<ymax>982</ymax>
		</bndbox>
	</object>
	<object>
		<name>purulent</name>
		<pose>Unspecified</pose>
		<truncated>0</truncated>
		<difficult>0</difficult>
		<occluded>0</occluded>
		<bndbox>
			<xmin>1018</xmin>
			<xmax>1073</xmax>
			<ymin>862</ymin>
			<ymax>1046</ymax>
		</bndbox>
	</object>
	<object>
		<name>purulent</name>
		<pose>Unspecified</pose>
		<truncated>0</truncated>
		<difficult>0</difficult>
		<occluded>0</occluded>
		<bndbox>
			<xmin>1043</xmin>
			<xmax>1082</xmax>
			<ymin>1044</ymin>
			<ymax>1191</ymax>
		</bndbox>
	</object>
	<object>
		<name>folliculitis</name>
		<pose>Unspecified</pose>
		<truncated>0</truncated>
		<difficult>0</difficult>
		<occluded>0</occluded>
		<bndbox>
			<xmin>891</xmin>
			<xmax>924</xmax>
			<ymin>1114</ymin>
			<ymax>1218</ymax>
		</bndbox>
	</object>
	<object>
		<name>purulent</name>
		<pose>Unspecified</pose>
		<truncated>0</truncated>
		<difficult>0</difficult>
		<occluded>0</occluded>
		<bndbox>
			<xmin>1139</xmin>
			<xmax>1168</xmax>
			<ymin>717</ymin>
			<ymax>773</ymax>
		</bndbox>
	</object>
	<object>
		<name>purulent</name>
		<pose>Unspecified</pose>
		<truncated>0</truncated>
		<difficult>0</difficult>
		<occluded>0</occluded>
		<bndbox>
			<xmin>1121</xmin>
			<xmax>1151</xmax>
			<ymin>827</ymin>
			<ymax>960</ymax>
		</bndbox>
	</object>
	<object>
		<name>purulent</name>
		<pose>Unspecified</pose>
		<truncated>0</truncated>
		<difficult>0</difficult>
		<occluded>0</occluded>
		<bndbox>
			<xmin>1115</xmin>
			<xmax>1147</xmax>
			<ymin>1099</ymin>
			<ymax>1220</ymax>
		</bndbox>
	</object>
	<object>
		<name>folliculitis</name>
		<pose>Unspecified</pose>
		<truncated>0</truncated>
		<difficult>0</difficult>
		<occluded>0</occluded>
		<bndbox>
			<xmin>1052</xmin>
			<xmax>1093</xmax>
			<ymin>1445</ymin>
			<ymax>1580</ymax>
		</bndbox>
	</object>
	<object>
		<name>sebo-crystan-conglo</name>
		<pose>Unspecified</pose>
		<truncated>0</truncated>
		<difficult>0</difficult>
		<occluded>0</occluded>
		<bndbox>
			<xmin>1181</xmin>
			<xmax>1233</xmax>
			<ymin>969</ymin>
			<ymax>1184</ymax>
		</bndbox>
	</object>
	<object>
		<name>sebo-crystan-conglo</name>
		<pose>Unspecified</pose>
		<truncated>0</truncated>
		<difficult>0</difficult>
		<occluded>0</occluded>
		<bndbox>
			<xmin>1186</xmin>
			<xmax>1224</xmax>
			<ymin>1327</ymin>
			<ymax>1511</ymax>
		</bndbox>
	</object>
	<object>
		<name>sebo-crystan-conglo</name>
		<pose>Unspecified</pose>
		<truncated>0</truncated>
		<difficult>0</difficult>
		<occluded>0</occluded>
		<bndbox>
			<xmin>785</xmin>
			<xmax>836</xmax>
			<ymin>1320</ymin>
			<ymax>1541</ymax>
		</bndbox>
	</object>
	<object>
		<name>sebo-crystan-conglo</name>
		<pose>Unspecified</pose>
		<truncated>0</truncated>
		<difficult>0</difficult>
		<occluded>0</occluded>
		<bndbox>
			<xmin>806</xmin>
			<xmax>861</xmax>
			<ymin>1547</ymin>
			<ymax>1707</ymax>
		</bndbox>
	</object>
	<object>
		<name>sebo-crystan-conglo</name>
		<pose>Unspecified</pose>
		<truncated>0</truncated>
		<difficult>0</difficult>
		<occluded>0</occluded>
		<bndbox>
			<xmin>756</xmin>
			<xmax>799</xmax>
			<ymin>949</ymin>
			<ymax>1184</ymax>
		</bndbox>
	</object>
	<object>
		<name>sebo-crystan-conglo</name>
		<pose>Unspecified</pose>
		<truncated>0</truncated>
		<difficult>0</difficult>
		<occluded>0</occluded>
		<bndbox>
			<xmin>833</xmin>
			<xmax>860</xmax>
			<ymin>1263</ymin>
			<ymax>1365</ymax>
		</bndbox>
	</object>
	<object>
		<name>purulent</name>
		<pose>Unspecified</pose>
		<truncated>0</truncated>
		<difficult>0</difficult>
		<occluded>0</occluded>
		<bndbox>
			<xmin>1110</xmin>
			<xmax>1151</xmax>
			<ymin>1415</ymin>
			<ymax>1542</ymax>
		</bndbox>
	</object>
	<object>
		<name>purulent</name>
		<pose>Unspecified</pose>
		<truncated>0</truncated>
		<difficult>0</difficult>
		<occluded>0</occluded>
		<bndbox>
			<xmin>1026</xmin>
			<xmax>1053</xmax>
			<ymin>1588</ymin>
			<ymax>1681</ymax>
		</bndbox>
	</object>
	<object>
		<name>purulent</name>
		<pose>Unspecified</pose>
		<truncated>0</truncated>
		<difficult>0</difficult>
		<occluded>0</occluded>
		<bndbox>
			<xmin>975</xmin>
			<xmax>1005</xmax>
			<ymin>1662</ymin>
			<ymax>1707</ymax>
		</bndbox>
	</object>
	<object>
		<name>purulent</name>
		<pose>Unspecified</pose>
		<truncated>0</truncated>
		<difficult>0</difficult>
		<occluded>0</occluded>
		<bndbox>
			<xmin>807</xmin>
			<xmax>857</xmax>
			<ymin>946</ymin>
			<ymax>1137</ymax>
		</bndbox>
	</object>
</annotation>
